yetiforce_python/__init__.py
YetiForce_Python-0.2.0.dist-info/LICENSE
YetiForce_Python-0.2.0.dist-info/METADATA
YetiForce_Python-0.2.0.dist-info/WHEEL
YetiForce_Python-0.2.0.dist-info/top_level.txt
YetiForce_Python-0.2.0.dist-info/RECORD
