Metadata-Version: 2.1
Name: YetiForce-Python
Version: 0.2.0
Summary: YetiForce CRM Python API Wrapper
Home-page: https://github.com/kbancerz/yetiforce-python
Author: Kajetan Bancerz
Author-email: kajetan.bancerz@gmail.com
License: MIT License
Requires-Dist: requests (>=2.21.0)
